opsml/__init__.py
opsml/app/__init__.py
opsml/app/core/__init__.py
opsml/app/core/dependencies.py
opsml/app/core/event_handlers.py
opsml/app/core/gunicorn.py
opsml/app/core/login.py
opsml/app/core/middleware.py
opsml/app/gunicorn_conf.py
opsml/app/main.py
opsml/app/routes/__init__.py
opsml/app/routes/audit.py
opsml/app/routes/auth.py
opsml/app/routes/cards.py
opsml/app/routes/data.py
opsml/app/routes/files.py
opsml/app/routes/healthcheck.py
opsml/app/routes/homepage.py
opsml/app/routes/metrics.py
opsml/app/routes/models.py
opsml/app/routes/projects.py
opsml/app/routes/pydantic_models.py
opsml/app/routes/registry.py
opsml/app/routes/route_helpers.py
opsml/app/routes/router.py
opsml/app/routes/utils.py
opsml/app/static/code_highlight/DIGESTS.md
opsml/app/static/code_highlight/LICENSE
opsml/app/static/code_highlight/README.md
opsml/app/static/code_highlight/es/core.js
opsml/app/static/code_highlight/es/core.min.js
opsml/app/static/code_highlight/es/highlight.js
opsml/app/static/code_highlight/es/highlight.min.js
opsml/app/static/code_highlight/es/package.json
opsml/app/static/code_highlight/highlight.js
opsml/app/static/code_highlight/highlight.min.js
opsml/app/static/code_highlight/languages/json.min.js
opsml/app/static/code_highlight/languages/markdown.min.js
opsml/app/static/code_highlight/languages/python.min.js
opsml/app/static/code_highlight/languages/sql.min.js
opsml/app/static/code_highlight/package.json
opsml/app/static/code_highlight/styles/stackoverflow-dark.css
opsml/app/static/code_highlight/styles/stackoverflow-dark.min.css
opsml/app/static/code_highlight/styles/stackoverflow-light.css
opsml/app/static/code_highlight/styles/stackoverflow-light.min.css
opsml/app/static/css/font.css
opsml/app/static/css/style.css
opsml/app/static/fonts/custom/bold.otf
opsml/app/static/fonts/custom/italic.otf
opsml/app/static/fonts/custom/medium.otf
opsml/app/static/fonts/custom/regular.otf
opsml/app/static/fonts/custom/semibold.otf
opsml/app/static/images/chip.png
opsml-2.3.0.dist-info/LICENSE.md
opsml-2.3.0.dist-info/METADATA
opsml-2.3.0.dist-info/WHEEL
opsml-2.3.0.dist-info/entry_points.txt
opsml-2.3.0.dist-info/RECORD
