Metadata-Version: 2.1
Name: opsml
Version: 2.3.0
Summary: Python MLOPs quality control tooling for your production ML workflows
Author: Steven Forrester
Author-email: steven.forrester@shipt.com
Requires-Python: >=3.9,<3.12
Classifier: Programming Language :: Python :: 3
Classifier: Programming Language :: Python :: 3.9
Classifier: Programming Language :: Python :: 3.10
Classifier: Programming Language :: Python :: 3.11
Provides-Extra: auth
Provides-Extra: gcp-mysql
Provides-Extra: gcp-postgres
Provides-Extra: gcs
Provides-Extra: mysql
Provides-Extra: postgres
Provides-Extra: profiling
Provides-Extra: s3
Provides-Extra: server
Provides-Extra: sklearn-onnx
Provides-Extra: tf-onnx
Provides-Extra: torch-onnx
Requires-Dist: PyJWT (==2.8.0) ; extra == "auth"
Requires-Dist: alembic (>=1.10.3,<2.0.0) ; extra == "server"
Requires-Dist: bcrypt (>=4.0.0,<5.0.0) ; extra == "auth"
Requires-Dist: boto3 (>=1.28,<2.0) ; extra == "s3"
Requires-Dist: cloud-sql-python-connector (>=1.2.0,<2.0.0) ; extra == "gcp-mysql" or extra == "gcp-postgres"
Requires-Dist: fastapi (>=0.109.0,<0.110.0) ; extra == "server"
Requires-Dist: fsspec (>=2023.1.0,<=2024.2.0)
Requires-Dist: gcsfs (>=2023.5.0,<2024.0.0) ; extra == "gcp-mysql" or extra == "gcp-postgres" or extra == "gcs"
Requires-Dist: gunicorn (>=20.1.0,<21.0.0) ; extra == "server"
Requires-Dist: httpx (>=0.23.3,<1.0.0)
Requires-Dist: jinja2 (>=3.1.2,<4.0.0) ; extra == "server"
Requires-Dist: joblib (>=1.3.2,<2.0.0)
Requires-Dist: onnx (>=1.16.0,<1.17.0) ; extra == "tf-onnx" or extra == "sklearn-onnx" or extra == "torch-onnx"
Requires-Dist: onnxmltools (>=1.11.1,<2.0.0) ; extra == "sklearn-onnx"
Requires-Dist: onnxruntime (>=1.16.0,<1.17.0) ; extra == "tf-onnx" or extra == "sklearn-onnx" or extra == "torch-onnx"
Requires-Dist: opsml-cli (>=0.5.0,<0.6.0)
Requires-Dist: pandas (>=1.5.3,<3)
Requires-Dist: pg8000 (>=1.29.4,<2.0.0) ; extra == "gcp-postgres"
Requires-Dist: polars (>=0.18.0,<0.19.0)
Requires-Dist: prometheus-fastapi-instrumentator (>=6.0.0,<7.0.0) ; extra == "server"
Requires-Dist: psutil (>=5.9.0,<6.0.0)
Requires-Dist: psycopg2 (>=2.9.6,<3.0.0) ; extra == "postgres"
Requires-Dist: pyarrow (>=10.0.0)
Requires-Dist: pydantic (>=2,<3)
Requires-Dist: pydantic_settings (>=2,<3)
Requires-Dist: pymysql (>=1.0.2,<2.0.0) ; extra == "gcp-mysql" or extra == "mysql"
Requires-Dist: python-multipart (>=0.0.7,<0.0.8) ; extra == "server"
Requires-Dist: pyyaml (>=6.0.1,<7.0.0)
Requires-Dist: rich (>=13.3.5,<14.0.0)
Requires-Dist: rollbar (>=0.16.3) ; extra == "server"
Requires-Dist: rusty-logger (>=0.3.0,<0.4.0)
Requires-Dist: s3fs (>=2023.5.0,<2024.0.0) ; extra == "s3"
Requires-Dist: semver (>=2.13.0,<3.0.0)
Requires-Dist: skl2onnx (>=1.15.0,<2.0.0,!=1.17.0) ; extra == "sklearn-onnx"
Requires-Dist: sqlalchemy[mypy] (>=2,<3) ; extra == "server"
Requires-Dist: streaming-form-data (>=1.11.0,<2.0.0) ; extra == "server"
Requires-Dist: tenacity (>=8.2.2,<9.0.0)
Requires-Dist: tf2onnx (>=1.16.1) ; extra == "tf-onnx"
Requires-Dist: uvicorn (>=0.24.0) ; extra == "server"
Requires-Dist: ydata-profiling (>=4.6.1,<5.0.0) ; extra == "profiling"
Requires-Dist: zarr (>2.12.0)
